Metadata-Version: 2.1
Name: exchangelib-listener
Version: 1.1.1
Summary: Simple inbox event listener for exchangelib.
Home-page: https://gitlab.com/evan_brown/exchangelib-listener
Author: Evan Brown
Author-email: evan.brown@ttigroupna.com
License: UNKNOWN
Platform: UNKNOWN
Classifier: Programming Language :: Python :: 3
Classifier: License :: OSI Approved :: MIT License
Classifier: Operating System :: OS Independent
Classifier: Intended Audience :: Developers
Requires-Python: >=3.8
